{
  "scanId": "scan-19d48679492-64f580a3",
  "target": "C:\\Users\\niran\\Downloads\\secret-sentry-master\\secret-sentry-master",
  "repoUrl": null,
  "repoName": null,
  "startedAt": "2026-04-01T09:37:20.890Z",
  "completedAt": "2026-04-01T09:37:21.042Z",
  "durationMs": 152,
  "summary": {
    "filesScanned": 168,
    "filesSkipped": 0,
    "totalIssues": 63,
    "bySeverity": {
      "critical": 28,
      "high": 30,
      "medium": 5,
      "low": 0
    }
  },
  "errors": [],
  "findings": [
    {
      "type": "GitHub Personal Access Token (Classic)",
      "severity": "critical",
      "file": "backend/app/api/v1/endpoints/cloud.py",
      "line": 369,
      "value": "ghp_********************************xxxx",
      "maskedValue": "ghp_********************************xxxx",
      "category": "github",
      "ruleId": "github-pat-classic",
      "confidence": 0.99,
      "isTestFile": false,
      "hash": "46eb12352e801d0b8907174aa272b0d9d4a414fef2e1c8be66ceab11910d7fd0",
      "snippet": "368: SENDGRID_API_KEY=SG.abcdefghijklmnop.qrstuvwxyz0123456789ABCDEFGH\n369: GITHUB_TOKEN=ghp_xxxxxxxxxxxxxxxxxxxxxxxxxxxxxxxxxxxx\n370: "
    },
    {
      "type": "PostgreSQL Connection String",
      "severity": "critical",
      "file": "backend/app/api/v1/endpoints/cloud.py",
      "line": 359,
      "value": "post**********************************************************tion",
      "maskedValue": "post**********************************************************tion",
      "category": "database",
      "ruleId": "postgres-connection",
      "confidence": 0.95,
      "isTestFile": false,
      "hash": "94bdb068c6066af44adcb4c10c10f389d1dd4ed707c6b0ae68d9e7223f59a1ea",
      "snippet": "358: # Database\n359: DATABASE_URL=postgres://admin:SuperSecretPass123@db.example.com:5432/production\n360: REDIS_URL=redis://default:RedisPass456@cache.example.com:6379"
    },
    {
      "type": "PostgreSQL Connection String",
      "severity": "critical",
      "file": "backend/app/integrations/aws_integration.py",
      "line": 764,
      "value": "post****************************t/db",
      "maskedValue": "post****************************t/db",
      "category": "database",
      "ruleId": "postgres-connection",
      "confidence": 0.95,
      "isTestFile": false,
      "hash": "af308d11eba47fbaa033df5e83c883ceb57ece4f67d40dae48aae1735e76cd42",
      "snippet": "763:         simulated_content = {\n764:             \"config/settings.json\": '{\"database_url\": \"postgres://user:pass123@localhost/db\"}',\n765:             \"src/app.py\": 'API_KEY = \"demo_api_key_1234567890abcdefghijklmnop\"',"
    },
    {
      "type": "RSA Private Key",
      "severity": "critical",
      "file": "backend/app/scanner/patterns.py",
      "line": 197,
      "value": "----************************************************************----",
      "maskedValue": "----************************************************************----",
      "category": "private_key",
      "ruleId": "rsa-private-key",
      "confidence": 0.99,
      "isTestFile": false,
      "hash": "a6fbc48d0aca1bc025e088761a92ba1968073cbbcc5bfed5cf387a81fe1d88b3",
      "snippet": "196:         name=\"RSA Private Key\",\n197:         pattern=r'-----BEGIN RSA PRIVATE KEY-----[\\s\\S]+?-----END RSA PRIVATE KEY-----',\n198:         category=SecretCategory.PRIVATE_KEY,"
    },
    {
      "type": "OpenSSH Private Key",
      "severity": "critical",
      "file": "backend/app/scanner/patterns.py",
      "line": 205,
      "value": "----********************************************************************----",
      "maskedValue": "----********************************************************************----",
      "category": "private_key",
      "ruleId": "openssh-private-key",
      "confidence": 0.99,
      "isTestFile": false,
      "hash": "b78cfe9ddd49a320f24e8091e9f843cc788ad61e50a17427aa13ca79382ec6c1",
      "snippet": "204:         name=\"OpenSSH Private Key\",\n205:         pattern=r'-----BEGIN OPENSSH PRIVATE KEY-----[\\s\\S]+?-----END OPENSSH PRIVATE KEY-----',\n206:         category=SecretCategory.PRIVATE_KEY,"
    },
    {
      "type": "EC Private Key",
      "severity": "critical",
      "file": "backend/app/scanner/patterns.py",
      "line": 221,
      "value": "----**********************************************************----",
      "maskedValue": "----**********************************************************----",
      "category": "private_key",
      "ruleId": "ec-private-key",
      "confidence": 0.99,
      "isTestFile": false,
      "hash": "31baec44f1bb12b665fd5a095252fdf78dcdad6a0c974f427b079101a7b2d6e8",
      "snippet": "220:         name=\"EC Private Key\",\n221:         pattern=r'-----BEGIN EC PRIVATE KEY-----[\\s\\S]+?-----END EC PRIVATE KEY-----',\n222:         category=SecretCategory.PRIVATE_KEY,"
    },
    {
      "type": "PGP Private Key",
      "severity": "critical",
      "file": "backend/app/scanner/patterns.py",
      "line": 229,
      "value": "----************************************************************************----",
      "maskedValue": "----************************************************************************----",
      "category": "private_key",
      "ruleId": "pgp-private-key",
      "confidence": 0.99,
      "isTestFile": false,
      "hash": "855d303f9cd732414c01ee18135279c1aa344ccc72b12e5aa5a19794eefea658",
      "snippet": "228:         name=\"PGP Private Key\",\n229:         pattern=r'-----BEGIN PGP PRIVATE KEY BLOCK-----[\\s\\S]+?-----END PGP PRIVATE KEY BLOCK-----',\n230:         category=SecretCategory.PRIVATE_KEY,"
    },
    {
      "type": "GitHub Personal Access Token (Classic)",
      "severity": "critical",
      "file": "backend/app/scanner/s3_scanner.py",
      "line": 125,
      "value": "ghp_********************************xxxx",
      "maskedValue": "ghp_********************************xxxx",
      "category": "github",
      "ruleId": "github-pat-classic",
      "confidence": 0.99,
      "isTestFile": false,
      "hash": "46eb12352e801d0b8907174aa272b0d9d4a414fef2e1c8be66ceab11910d7fd0",
      "snippet": "124:             (\"scripts/backup.sh\", 768, 'DB_PASSWORD=\"SuperSecret123!\"\\nencryption_key=\"mybase64encryptedkey==\"'),\n125:             (\"terraform/main.tf\", 2560, 'secret_key = \"ghp_xxxxxxxxxxxxxxxxxxxxxxxxxxxxxxxxxxxx\"'),\n126:             (\"docs/README.md\", 1536, \"# API Documentation\\nNo secrets here\"),"
    },
    {
      "type": "PostgreSQL Connection String",
      "severity": "critical",
      "file": "backend/app/scanner/s3_scanner.py",
      "line": 120,
      "value": "post****************************t/db",
      "maskedValue": "post****************************t/db",
      "category": "database",
      "ruleId": "postgres-connection",
      "confidence": 0.95,
      "isTestFile": false,
      "hash": "af308d11eba47fbaa033df5e83c883ceb57ece4f67d40dae48aae1735e76cd42",
      "snippet": "119:         simulated_files = [\n120:             (\"config/settings.json\", 2048, '{\"database_url\": \"postgres://user:pass123@localhost/db\"}'),\n121:             (\"src/api/auth.py\", 4096, 'API_KEY = \"demo_api_key_1234567890abcdefghijklmnop\"'),"
    },
    {
      "type": "PostgreSQL Connection String",
      "severity": "critical",
      "file": "backend/app/scanner/s3_scanner.py",
      "line": 157,
      "value": "post**********************************************************yapp",
      "maskedValue": "post**********************************************************yapp",
      "category": "database",
      "ruleId": "postgres-connection",
      "confidence": 0.95,
      "isTestFile": false,
      "hash": "2e9c47b9d60630d018efa5e9cd491b3019d4af44c2e57c60a2882cf648619464",
      "snippet": "156:     \"app_name\": \"MyApp\",\n157:     \"database_url\": \"postgres://admin:SuperSecretPass123@prod-db.example.com:5432/myapp\",\n158:     \"redis_url\": \"redis://default:RedisPassword456@cache.example.com:6379\","
    },
    {
      "type": "PostgreSQL Connection String",
      "severity": "critical",
      "file": "backend/app/scanner/s3_scanner.py",
      "line": 173,
      "value": "post**********************************************************tion",
      "maskedValue": "post**********************************************************tion",
      "category": "database",
      "ruleId": "postgres-connection",
      "confidence": 0.95,
      "isTestFile": false,
      "hash": "109c956b17a640d79930e06cd6205c09744626fab0794d9375d75a89a95c0304",
      "snippet": "172:             \".env.production\": b'''# Production Environment Variables\n173: DATABASE_URL=postgres://prod_user:Pr0d_P@ssw0rd!@db.example.com:5432/production\n174: AWS_ACCESS_KEY_ID=EXAMPLE_AWS_KEY_ID_12345"
    },
    {
      "type": "PostgreSQL Connection String",
      "severity": "critical",
      "file": "frontend/src/lib/demoData.ts",
      "line": 122,
      "value": "post*****************@...",
      "maskedValue": "post*****************@...",
      "category": "database",
      "ruleId": "postgres-connection",
      "confidence": 0.95,
      "isTestFile": false,
      "hash": "2f8d8a9b84084b3f344009f36bb30ff263a6673426c71b0285343c7c3369bea1",
      "snippet": "121:     line_number: 45,\n122:     masked_value: 'postgres://admin:****@...',\n123:     environment: 'staging',"
    },
    {
      "type": "AWS Access Key ID",
      "severity": "critical",
      "file": "report.html",
      "line": 502,
      "value": "AKIA************MPLE",
      "maskedValue": "AKIA************MPLE",
      "category": "aws",
      "ruleId": "aws-access-key-id",
      "confidence": 0.95,
      "isTestFile": false,
      "hash": "1a5d44a2dca19669d72edf4c4f1c27c4c1ca4b4408fbb17f6ce4ad452d78ddb3",
      "snippet": "501:       <pre class=\"snippet\" id=\"snippet-0\">7: // AWS Access Key (fake) — direct identifier, not in a string\n502: 8: const AWS_ACCESS_KEY = &#39;AKIAIOSFODNN7EXAMPLE&#39;;\n503: 9: </pre></td>"
    },
    {
      "type": "GitHub Personal Access Token (Classic)",
      "severity": "critical",
      "file": "report.html",
      "line": 554,
      "value": "ghp_********************************gh12",
      "maskedValue": "ghp_********************************gh12",
      "category": "github",
      "ruleId": "github-pat-classic",
      "confidence": 0.99,
      "isTestFile": false,
      "hash": "e00fc38974e9f3ce02fe40aeedab55be474ffbd3a4bd1206d7f07147615acdd8",
      "snippet": "553:       <pre class=\"snippet\" id=\"snippet-2\">13: // GitHub PAT (fake)\n554: 14: const GITHUB_TOKEN = &#39;ghp_ABCDEFGHIJKLMNOPQRSTUVWXYZabcdefgh12&#39;;\n555: 15: </pre></td>"
    },
    {
      "type": "PostgreSQL Connection String",
      "severity": "critical",
      "file": "report.html",
      "line": 580,
      "value": "post*****************************************************39;;",
      "maskedValue": "post*****************************************************39;;",
      "category": "database",
      "ruleId": "postgres-connection",
      "confidence": 0.95,
      "isTestFile": false,
      "hash": "3918b9879b50d9da923a25424c20063da5a49ec3285dcd37a1c6a97f4e0df6ef",
      "snippet": "579:       <pre class=\"snippet\" id=\"snippet-3\">31: // PostgreSQL DSN (fake)\n580: 32: const dbUrl = &#39;postgres://admin:SecretPass123@db.example.com:5432/mydb&#39;;\n581: 33: </pre></td>"
    },
    {
      "type": "Stripe API Key",
      "severity": "critical",
      "file": "report.html",
      "line": 606,
      "value": "sk_l*****************************************6789",
      "maskedValue": "sk_l*****************************************6789",
      "category": "api_key",
      "ruleId": "stripe-key",
      "confidence": 0.99,
      "isTestFile": false,
      "hash": "2aae6d77cafd928130f9b5612cf45c8bfcff8909b85628812b7694b679355d9f",
      "snippet": "605:       <pre class=\"snippet\" id=\"snippet-4\">25: // Stripe key (fake) — actual value\n606: 26: const stripeKey = &#39;sk_live_51ABCDEFGHIJKLMNOPQRSTUVWXYZtest123456789&#39;;\n607: 27: </pre></td>"
    },
    {
      "type": "NPM Access Token",
      "severity": "critical",
      "file": "report.html",
      "line": 632,
      "value": "npm_********************************gh12",
      "maskedValue": "npm_********************************gh12",
      "category": "api_key",
      "ruleId": "npm-token",
      "confidence": 0.99,
      "isTestFile": false,
      "hash": "fcfc7b8bbb52d6ff1fc924e1458ed1e8af4b94eea527d5a8969bf676978d681b",
      "snippet": "631:       <pre class=\"snippet\" id=\"snippet-5\">34: // NPM token (fake)\n632: 35: const npmToken = &#39;npm_ABCDEFGHIJKLMNOPQRSTUVWXYZabcdefgh12&#39;;\n633: 36: </pre></td>"
    },
    {
      "type": "AWS Access Key ID",
      "severity": "critical",
      "file": "scanner/README.md",
      "line": 94,
      "value": "AKIA************MPLE",
      "maskedValue": "AKIA************MPLE",
      "category": "aws",
      "ruleId": "aws-access-key-id",
      "confidence": 0.95,
      "isTestFile": false,
      "hash": "1a5d44a2dca19669d72edf4c4f1c27c4c1ca4b4408fbb17f6ce4ad452d78ddb3",
      "snippet": "93:       \"hash\": \"sha256-of-raw-value\",\n94:       \"snippet\": \"11: // config\\n12: const key = 'AKIAIOSFODNN7EXAMPLE';\\n13: module.exports = { key };\"\n95:     }"
    },
    {
      "type": "RSA Private Key",
      "severity": "critical",
      "file": "scanner/rules.js",
      "line": 184,
      "value": "----************************************************************----",
      "maskedValue": "----************************************************************----",
      "category": "private_key",
      "ruleId": "rsa-private-key",
      "confidence": 0.99,
      "isTestFile": false,
      "hash": "a6fbc48d0aca1bc025e088761a92ba1968073cbbcc5bfed5cf387a81fe1d88b3",
      "snippet": "183:     confidence: 0.99,\n184:     pattern: /-----BEGIN RSA PRIVATE KEY-----[\\s\\S]+?-----END RSA PRIVATE KEY-----/g,\n185:     description: 'RSA Private Key',"
    },
    {
      "type": "OpenSSH Private Key",
      "severity": "critical",
      "file": "scanner/rules.js",
      "line": 193,
      "value": "----********************************************************************----",
      "maskedValue": "----********************************************************************----",
      "category": "private_key",
      "ruleId": "openssh-private-key",
      "confidence": 0.99,
      "isTestFile": false,
      "hash": "b78cfe9ddd49a320f24e8091e9f843cc788ad61e50a17427aa13ca79382ec6c1",
      "snippet": "192:     confidence: 0.99,\n193:     pattern: /-----BEGIN OPENSSH PRIVATE KEY-----[\\s\\S]+?-----END OPENSSH PRIVATE KEY-----/g,\n194:     description: 'OpenSSH Private Key',"
    },
    {
      "type": "EC Private Key",
      "severity": "critical",
      "file": "scanner/rules.js",
      "line": 202,
      "value": "----**********************************************************----",
      "maskedValue": "----**********************************************************----",
      "category": "private_key",
      "ruleId": "ec-private-key",
      "confidence": 0.99,
      "isTestFile": false,
      "hash": "31baec44f1bb12b665fd5a095252fdf78dcdad6a0c974f427b079101a7b2d6e8",
      "snippet": "201:     confidence: 0.99,\n202:     pattern: /-----BEGIN EC PRIVATE KEY-----[\\s\\S]+?-----END EC PRIVATE KEY-----/g,\n203:     description: 'Elliptic Curve Private Key',"
    },
    {
      "type": "PGP Private Key",
      "severity": "critical",
      "file": "scanner/rules.js",
      "line": 211,
      "value": "----************************************************************************----",
      "maskedValue": "----************************************************************************----",
      "category": "private_key",
      "ruleId": "pgp-private-key",
      "confidence": 0.99,
      "isTestFile": false,
      "hash": "855d303f9cd732414c01ee18135279c1aa344ccc72b12e5aa5a19794eefea658",
      "snippet": "210:     confidence: 0.99,\n211:     pattern: /-----BEGIN PGP PRIVATE KEY BLOCK-----[\\s\\S]+?-----END PGP PRIVATE KEY BLOCK-----/g,\n212:     description: 'PGP Private Key Block',"
    },
    {
      "type": "AWS Access Key ID",
      "severity": "critical",
      "file": "scanner/test/fixtures/fake_secrets.js",
      "line": 8,
      "value": "AKIA************MPLE",
      "maskedValue": "AKIA************MPLE",
      "category": "aws",
      "ruleId": "aws-access-key-id",
      "confidence": 0.95,
      "isTestFile": true,
      "hash": "1a5d44a2dca19669d72edf4c4f1c27c4c1ca4b4408fbb17f6ce4ad452d78ddb3",
      "snippet": "7: // AWS Access Key (fake) — direct identifier, not in a string\n8: const AWS_ACCESS_KEY = 'AKIAIOSFODNN7EXAMPLE';\n9: "
    },
    {
      "type": "AWS Secret Access Key",
      "severity": "critical",
      "file": "scanner/test/fixtures/fake_secrets.js",
      "line": 11,
      "value": "wJal********************************EKEY",
      "maskedValue": "wJal********************************EKEY",
      "category": "aws",
      "ruleId": "aws-secret-access-key",
      "confidence": 0.9,
      "isTestFile": true,
      "hash": "78314b11be2e581549ac1c4f616563fad3fdf0c3b71678f6e2299182080e0598",
      "snippet": "10: // AWS Secret Access Key (fake) — env-var style assignment\n11: // aws_secret_access_key = \"wJalrXUtnFEMI/K7MDENG/bPxRfiCYEXAMPLEKEY\"\n12: "
    },
    {
      "type": "GitHub Personal Access Token (Classic)",
      "severity": "critical",
      "file": "scanner/test/fixtures/fake_secrets.js",
      "line": 14,
      "value": "ghp_********************************gh12",
      "maskedValue": "ghp_********************************gh12",
      "category": "github",
      "ruleId": "github-pat-classic",
      "confidence": 0.99,
      "isTestFile": true,
      "hash": "e00fc38974e9f3ce02fe40aeedab55be474ffbd3a4bd1206d7f07147615acdd8",
      "snippet": "13: // GitHub PAT (fake)\n14: const GITHUB_TOKEN = 'ghp_ABCDEFGHIJKLMNOPQRSTUVWXYZabcdefgh12';\n15: "
    },
    {
      "type": "PostgreSQL Connection String",
      "severity": "critical",
      "file": "scanner/test/fixtures/fake_secrets.js",
      "line": 32,
      "value": "post***********************************************mydb",
      "maskedValue": "post***********************************************mydb",
      "category": "database",
      "ruleId": "postgres-connection",
      "confidence": 0.95,
      "isTestFile": true,
      "hash": "509a5cb43736a2779a73cc160a0708b076499d7acf6a4902580aa25e6575c107",
      "snippet": "31: // PostgreSQL DSN (fake)\n32: const dbUrl = 'postgres://admin:SecretPass123@db.example.com:5432/mydb';\n33: "
    },
    {
      "type": "Stripe API Key",
      "severity": "critical",
      "file": "scanner/test/fixtures/fake_secrets.js",
      "line": 26,
      "value": "sk_l*****************************************6789",
      "maskedValue": "sk_l*****************************************6789",
      "category": "api_key",
      "ruleId": "stripe-key",
      "confidence": 0.99,
      "isTestFile": true,
      "hash": "2aae6d77cafd928130f9b5612cf45c8bfcff8909b85628812b7694b679355d9f",
      "snippet": "25: // Stripe key (fake) — actual value\n26: const stripeKey = 'sk_live_51ABCDEFGHIJKLMNOPQRSTUVWXYZtest123456789';\n27: "
    },
    {
      "type": "NPM Access Token",
      "severity": "critical",
      "file": "scanner/test/fixtures/fake_secrets.js",
      "line": 35,
      "value": "npm_********************************gh12",
      "maskedValue": "npm_********************************gh12",
      "category": "api_key",
      "ruleId": "npm-token",
      "confidence": 0.99,
      "isTestFile": true,
      "hash": "fcfc7b8bbb52d6ff1fc924e1458ed1e8af4b94eea527d5a8969bf676978d681b",
      "snippet": "34: // NPM token (fake)\n35: const npmToken = 'npm_ABCDEFGHIJKLMNOPQRSTUVWXYZabcdefgh12';\n36: "
    },
    {
      "type": "JWT Token",
      "severity": "high",
      "file": "backend/.env.example",
      "line": 11,
      "value": "eyJh********************************************************************************************************************************************************************************************************48Pc",
      "maskedValue": "eyJh********************************************************************************************************************************************************************************************************48Pc",
      "category": "jwt",
      "ruleId": "jwt-token",
      "confidence": 0.95,
      "isTestFile": true,
      "hash": "f3fcc16c7fcb01e447b3607ca922b63398fd0198d2d7bf6f7b9af1a118bab0b7",
      "snippet": "10: SUPABASE_URL=https://twcrpnrzgeqraajxyyqe.supabase.co\n11: SUPABASE_KEY=eyJhbGciOiJIUzI1NiIsInR5cCI6IkpXVCJ9.eyJpc3MiOiJzdXBhYmFzZSIsInJlZiI6InR3Y3JwbnJ6Z2VxcmFhanh5eXFlIiwicm9sZSI6ImFub24iLCJpYXQiOjE3NzA4NTczNTQsImV4cCI6MjA4NjQzMzM1NH0.jPcv98C3V0Q5WOqiIcul_KJKDS_WsLmD7ywskj848Pc\n12: # Service role key for backend operations (bypasses RLS)"
    },
    {
      "type": "Redis Connection String",
      "severity": "high",
      "file": "backend/app/api/v1/endpoints/cloud.py",
      "line": 360,
      "value": "redi*******************************************6379",
      "maskedValue": "redi*******************************************6379",
      "category": "database",
      "ruleId": "redis-connection",
      "confidence": 0.9,
      "isTestFile": false,
      "hash": "8b6c276fdb9e38a15c58c01ea5a7379bd4816f43ea8271e185665bcc6d9909e0",
      "snippet": "359: DATABASE_URL=postgres://admin:SuperSecretPass123@db.example.com:5432/production\n360: REDIS_URL=redis://default:RedisPass456@cache.example.com:6379\n361: "
    },
    {
      "type": "SendGrid API Key",
      "severity": "high",
      "file": "backend/app/api/v1/endpoints/cloud.py",
      "line": 368,
      "value": "SG.a****************************************EFGH",
      "maskedValue": "SG.a****************************************EFGH",
      "category": "api_key",
      "ruleId": "sendgrid-key",
      "confidence": 0.99,
      "isTestFile": false,
      "hash": "0cb7482f8b85b42ad3d40a888f3ff14f3082b6e3fcd25089f5f580cbaac221b6",
      "snippet": "367: STRIPE_SECRET_KEY=demo_stripe_api_key_placeholder_value\n368: SENDGRID_API_KEY=SG.abcdefghijklmnop.qrstuvwxyz0123456789ABCDEFGH\n369: GITHUB_TOKEN=ghp_xxxxxxxxxxxxxxxxxxxxxxxxxxxxxxxxxxxx"
    },
    {
      "type": "Azure AD Client Secret",
      "severity": "high",
      "file": "backend/app/api/v1/endpoints/cloud.py",
      "line": 373,
      "value": "GOCS***************************xxxx",
      "maskedValue": "GOCS***************************xxxx",
      "category": "azure",
      "ruleId": "azure-client-secret",
      "confidence": 0.7,
      "isTestFile": false,
      "hash": "3eaa55d0658b9ff900344b8d1f021459cfe7abc315dcf61ecf16e18d438c4033",
      "snippet": "372: JWT_SECRET=my-super-secret-jwt-signing-key-should-be-longer\n373: GOOGLE_CLIENT_SECRET=GOCSPX-xxxxxxxxxxxxxxxxxxxxxxxxxxxx\n374: "
    },
    {
      "type": "Hardcoded Password",
      "severity": "high",
      "file": "backend/app/models/secret.py",
      "line": 23,
      "value": "********",
      "maskedValue": "********",
      "category": "password",
      "ruleId": "hardcoded-password",
      "confidence": 0.7,
      "isTestFile": false,
      "hash": "5e884898da28047151d0e56f8dc6292773603d0d6aabbdd62a11ef721d1542d8",
      "snippet": "22:     JWT_TOKEN = \"jwt_token\"\n23:     PASSWORD = \"password\"\n24:     DATABASE_URL = \"database_url\""
    },
    {
      "type": "Hardcoded Password",
      "severity": "high",
      "file": "backend/app/scanner/patterns.py",
      "line": 22,
      "value": "********",
      "maskedValue": "********",
      "category": "password",
      "ruleId": "hardcoded-password",
      "confidence": 0.7,
      "isTestFile": false,
      "hash": "5e884898da28047151d0e56f8dc6292773603d0d6aabbdd62a11ef721d1542d8",
      "snippet": "21:     API_KEY = \"api_key\"\n22:     PASSWORD = \"password\"\n23:     OAUTH = \"oauth\""
    },
    {
      "type": "Redis Connection String",
      "severity": "high",
      "file": "backend/app/scanner/s3_scanner.py",
      "line": 158,
      "value": "redi***********************************************6379",
      "maskedValue": "redi***********************************************6379",
      "category": "database",
      "ruleId": "redis-connection",
      "confidence": 0.9,
      "isTestFile": false,
      "hash": "347e82959006a78f75811e3e3c78edb29c23119d652ecabdf7dc7f180d5f94df",
      "snippet": "157:     \"database_url\": \"postgres://admin:SuperSecretPass123@prod-db.example.com:5432/myapp\",\n158:     \"redis_url\": \"redis://default:RedisPassword456@cache.example.com:6379\",\n159:     \"api_base_url\": \"https://api.example.com\""
    },
    {
      "type": "Hardcoded Password",
      "severity": "high",
      "file": "backend/app/scanner/s3_scanner.py",
      "line": 124,
      "value": "Supe*******123!",
      "maskedValue": "Supe*******123!",
      "category": "password",
      "ruleId": "hardcoded-password",
      "confidence": 0.7,
      "isTestFile": false,
      "hash": "f287fa343b2b4aceec2054c03246e3050ef9ff3c8d8a4a5577a8e84071ea5b2a",
      "snippet": "123:             (\"deploy/secrets.yaml\", 1024, 'stripe_key: demo_stripe_key_abc123\\ngoogle_api: demo_google_api_key_1234'),\n124:             (\"scripts/backup.sh\", 768, 'DB_PASSWORD=\"SuperSecret123!\"\\nencryption_key=\"mybase64encryptedkey==\"'),\n125:             (\"terraform/main.tf\", 2560, 'secret_key = \"ghp_xxxxxxxxxxxxxxxxxxxxxxxxxxxxxxxxxxxx\"'),"
    },
    {
      "type": "Hardcoded Password",
      "severity": "high",
      "file": "backend/app/scanner/s3_scanner.py",
      "line": 194,
      "value": "Back***********024!",
      "maskedValue": "Back***********024!",
      "category": "password",
      "ruleId": "hardcoded-password",
      "confidence": 0.7,
      "isTestFile": false,
      "hash": "03fc9f55f013d287fa8ff747ed0d283ba8bb10a82285fe3be5d68e3dff2acd7c",
      "snippet": "193: DB_USER=\"backup_user\"\n194: DB_PASSWORD=\"BackupP@ssw0rd2024!\"\n195: "
    },
    {
      "type": "Hardcoded Secret Key",
      "severity": "high",
      "file": "backend/app/scanner/s3_scanner.py",
      "line": 125,
      "value": "ghp_********************************xxxx",
      "maskedValue": "ghp_********************************xxxx",
      "category": "password",
      "ruleId": "hardcoded-secret-key",
      "confidence": 0.75,
      "isTestFile": false,
      "hash": "46eb12352e801d0b8907174aa272b0d9d4a414fef2e1c8be66ceab11910d7fd0",
      "snippet": "124:             (\"scripts/backup.sh\", 768, 'DB_PASSWORD=\"SuperSecret123!\"\\nencryption_key=\"mybase64encryptedkey==\"'),\n125:             (\"terraform/main.tf\", 2560, 'secret_key = \"ghp_xxxxxxxxxxxxxxxxxxxxxxxxxxxxxxxxxxxx\"'),\n126:             (\"docs/README.md\", 1536, \"# API Documentation\\nNo secrets here\"),"
    },
    {
      "type": "Hardcoded Secret Key",
      "severity": "high",
      "file": "backend/app/scanner/s3_scanner.py",
      "line": 206,
      "value": "wJal********************************EKEY",
      "maskedValue": "wJal********************************EKEY",
      "category": "password",
      "ruleId": "hardcoded-secret-key",
      "confidence": 0.75,
      "isTestFile": false,
      "hash": "78314b11be2e581549ac1c4f616563fad3fdf0c3b71678f6e2299182080e0598",
      "snippet": "205:   access_key = \"EXAMPLE_AWS_KEY_ID_12345\"\n206:   secret_key = \"wJalrXUtnFEMI/K7MDENG/bPxRfiCYEXAMPLEKEY\"\n207: }"
    },
    {
      "type": "Slack Webhook URL",
      "severity": "high",
      "file": "backend/app/scanner/s3_scanner.py",
      "line": 178,
      "value": "http***********************************************XXXX",
      "maskedValue": "http***********************************************XXXX",
      "category": "api_key",
      "ruleId": "slack-webhook",
      "confidence": 0.99,
      "isTestFile": false,
      "hash": "848582102d27502b9de18184a356096e7802b1932c86afad4a55a777bf8c4493",
      "snippet": "177: JWT_SECRET=my-super-secret-jwt-key-that-should-not-be-here\n178: SLACK_WEBHOOK=https://hooks.slack.com/services/T00000/B00000/XXXXXXXX\n179: ''',"
    },
    {
      "type": "SendGrid API Key",
      "severity": "high",
      "file": "backend/app/scanner/s3_scanner.py",
      "line": 166,
      "value": "SG.a****************************************EFGH",
      "maskedValue": "SG.a****************************************EFGH",
      "category": "api_key",
      "ruleId": "sendgrid-key",
      "confidence": 0.99,
      "isTestFile": false,
      "hash": "0cb7482f8b85b42ad3d40a888f3ff14f3082b6e3fcd25089f5f580cbaac221b6",
      "snippet": "165: STRIPE_API_KEY = \"demo_stripe_api_key_placeholder_value\"\n166: SENDGRID_KEY = \"SG.abcdefghijklmnop.qrstuvwxyz0123456789ABCDEFGH\"\n167: "
    },
    {
      "type": "Hardcoded Password",
      "severity": "high",
      "file": "backend/test_scanner.py",
      "line": 24,
      "value": "supe****************d123",
      "maskedValue": "supe****************d123",
      "category": "password",
      "ruleId": "hardcoded-password",
      "confidence": 0.7,
      "isTestFile": true,
      "hash": "867d59e8e0b27e5c9e2b896d520253a9b8fc88eccd3c8d561e015e7fc1b9a696",
      "snippet": "23: api_key = \"example_api_key_1234567890\"\n24: password = \"super_secret_password123\"\n25: github_token = \"ghp_example_token_placeholder_xxxxx\""
    },
    {
      "type": "Hardcoded Secret Key",
      "severity": "high",
      "file": "backend/test_scanner.py",
      "line": 22,
      "value": "exam***********************************tion",
      "maskedValue": "exam***********************************tion",
      "category": "password",
      "ruleId": "hardcoded-secret-key",
      "confidence": 0.75,
      "isTestFile": true,
      "hash": "8f9ff649dcfb8fa26980ac64e786e4f415401a46dc4f3fa270b04867486ecac9",
      "snippet": "21: AWS_ACCESS_KEY_ID = \"AKIA_EXAMPLE_KEY_12345\"\n22: secret_key = \"example_secret_key_do_not_use_in_production\"\n23: api_key = \"example_api_key_1234567890\""
    },
    {
      "type": "Redis Connection String",
      "severity": "high",
      "file": "docker-compose.yml",
      "line": 56,
      "value": "redi*****************************************79/0",
      "maskedValue": "redi*****************************************79/0",
      "category": "database",
      "ruleId": "redis-connection",
      "confidence": 0.9,
      "isTestFile": false,
      "hash": "81054bc6b7c178abf44158d8d442387a39f8a0f4b3c3ce6cf923349c40ddc2e2",
      "snippet": "55:       # Redis\n56:       REDIS_URL: redis://:${REDIS_PASSWORD:-redis123}@redis:6379/0\n57:       "
    },
    {
      "type": "Hardcoded Password",
      "severity": "high",
      "file": "frontend/src/app/login/page.tsx",
      "line": 36,
      "value": "Pass************ired",
      "maskedValue": "Pass************ired",
      "category": "password",
      "ruleId": "hardcoded-password",
      "confidence": 0.7,
      "isTestFile": false,
      "hash": "7aeae1412484f6378e5877b660a41baa6a521988eb8b2620ca3223b05e2ff20c",
      "snippet": "35:     if (!password) {\n36:       newErrors.password = 'Password is required'\n37:     } else if (password.length < 6) {"
    },
    {
      "type": "Hardcoded Password",
      "severity": "high",
      "file": "frontend/src/app/login/page.tsx",
      "line": 38,
      "value": "Pass******************************ters",
      "maskedValue": "Pass******************************ters",
      "category": "password",
      "ruleId": "hardcoded-password",
      "confidence": 0.7,
      "isTestFile": false,
      "hash": "2005290ddda9a56d32aaa84e434f3d2ffa1ed268cb8228a39173cafd08eada4e",
      "snippet": "37:     } else if (password.length < 6) {\n38:       newErrors.password = 'Password must be at least 6 characters'\n39:     }"
    },
    {
      "type": "Hardcoded Password",
      "severity": "high",
      "file": "frontend/src/app/register/page.tsx",
      "line": 47,
      "value": "Pass************ired",
      "maskedValue": "Pass************ired",
      "category": "password",
      "ruleId": "hardcoded-password",
      "confidence": 0.7,
      "isTestFile": false,
      "hash": "7aeae1412484f6378e5877b660a41baa6a521988eb8b2620ca3223b05e2ff20c",
      "snippet": "46:     if (!password) {\n47:       newErrors.password = 'Password is required'\n48:     } else if (!passwordRequirements.every(r => r.met)) {"
    },
    {
      "type": "Hardcoded Password",
      "severity": "high",
      "file": "frontend/src/app/register/page.tsx",
      "line": 49,
      "value": "Pass***************************ents",
      "maskedValue": "Pass***************************ents",
      "category": "password",
      "ruleId": "hardcoded-password",
      "confidence": 0.7,
      "isTestFile": false,
      "hash": "19ffc3311f3ef96f346e7ccdbbff3b04b34b9027aa679ea8ad4e14fd3ab93ed9",
      "snippet": "48:     } else if (!passwordRequirements.every(r => r.met)) {\n49:       newErrors.password = 'Password does not meet requirements'\n50:     }"
    },
    {
      "type": "Hardcoded Password",
      "severity": "high",
      "file": "frontend/src/app/register/page.tsx",
      "line": 52,
      "value": "Pass**************atch",
      "maskedValue": "Pass**************atch",
      "category": "password",
      "ruleId": "hardcoded-password",
      "confidence": 0.7,
      "isTestFile": false,
      "hash": "b6eb82cd3300c838f99773b371b2f81d5ad517b3ba903de637d3e5920de7c04f",
      "snippet": "51:     if (password !== confirmPassword) {\n52:       newErrors.confirmPassword = 'Passwords do not match'\n53:     }"
    },
    {
      "type": "Hardcoded Password",
      "severity": "high",
      "file": "frontend/src/contexts/AuthContext.tsx",
      "line": 160,
      "value": "Demo**024!",
      "maskedValue": "Demo**024!",
      "category": "password",
      "ruleId": "hardcoded-password",
      "confidence": 0.7,
      "isTestFile": false,
      "hash": "77d2967b2d7203169ed13d71936da945638ab33d780197e12c6fa6956762e832",
      "snippet": "159:   const DEMO_EMAIL = 'demo@vaultsentry.io'\n160:   const DEMO_PASSWORD = 'Demo@2024!'\n161: "
    },
    {
      "type": "Hardcoded Secret Key",
      "severity": "high",
      "file": "README.md",
      "line": 149,
      "value": "your********************hars",
      "maskedValue": "your********************hars",
      "category": "password",
      "ruleId": "hardcoded-secret-key",
      "confidence": 0.75,
      "isTestFile": false,
      "hash": "b3009e99479d219bc16be6eb89b385e79cb03c7c12793aa8904e846afde14d9b",
      "snippet": "148: export REDIS_URL=\"redis://localhost:6379/0\"\n149: export SECRET_KEY=\"your-secret-key-min-32-chars\"\n150: "
    },
    {
      "type": "JWT Token",
      "severity": "high",
      "file": "report.html",
      "line": 658,
      "value": "eyJh****************************************************************************************************************************sw5c",
      "maskedValue": "eyJh****************************************************************************************************************************sw5c",
      "category": "jwt",
      "ruleId": "jwt-token",
      "confidence": 0.95,
      "isTestFile": false,
      "hash": "725331a2172e9231d1dead7c7dcf737a2381418aff4cc9e9ce75e87bdeb22f4d",
      "snippet": "657:       <pre class=\"snippet\" id=\"snippet-6\">16: // JWT Token (fake)\n658: 17: const JWT = &#39;eyJhbGciOiJIUzI1NiIsInR5cCI6IkpXVCJ9.eyJzdWIiOiIxMjM0NTY3ODkwIiwibmFtZSI6IkpvaG4gRG9lIn0.SflKxwRJSMeKKF2QT4fwpMeJf36POk6yJV_adQssw5c&#39;;\n659: 18: </pre></td>"
    },
    {
      "type": "Slack Webhook URL",
      "severity": "high",
      "file": "report.html",
      "line": 710,
      "value": "http***************************************************************************xxxx",
      "maskedValue": "http***************************************************************************xxxx",
      "category": "api_key",
      "ruleId": "slack-webhook",
      "confidence": 0.99,
      "isTestFile": false,
      "hash": "c99ff66649400eb10adfefc048b4a074d3298fef5ba99c6aaa276999a2896cb7",
      "snippet": "709:       <pre class=\"snippet\" id=\"snippet-8\">28: // Slack webhook (fake)\n710: 29: const slackWebhook = &#39;https://hooks.slack.com/services/TABCDEF123/BABCDEF456/xxxxxxxxxxxxxxxxxxxxxxxxxxxx&#39;;\n711: 30: </pre></td>"
    },
    {
      "type": "SendGrid API Key",
      "severity": "high",
      "file": "report.html",
      "line": 736,
      "value": "SG.A**********************************************************6789",
      "maskedValue": "SG.A**********************************************************6789",
      "category": "api_key",
      "ruleId": "sendgrid-key",
      "confidence": 0.99,
      "isTestFile": false,
      "hash": "5f6f704cb6858e3d03f582dbaef3c339b05d9d4a73697fda26c1cd32765eaca3",
      "snippet": "735:       <pre class=\"snippet\" id=\"snippet-9\">37: // SendGrid key (fake)\n736: 38: const sgKey = &#39;SG.ABCDEFGHIJKLMNOPQRSTUVWX.YZABCDEFGHIJKLMNOPQRSTUVWXYZ0123456789&#39;;\n737: 39: </pre></td>"
    },
    {
      "type": "JWT Token",
      "severity": "high",
      "file": "scanner/test/fixtures/fake_secrets.js",
      "line": 17,
      "value": "eyJh****************************************************************************************************************************sw5c",
      "maskedValue": "eyJh****************************************************************************************************************************sw5c",
      "category": "jwt",
      "ruleId": "jwt-token",
      "confidence": 0.95,
      "isTestFile": true,
      "hash": "725331a2172e9231d1dead7c7dcf737a2381418aff4cc9e9ce75e87bdeb22f4d",
      "snippet": "16: // JWT Token (fake)\n17: const JWT = 'eyJhbGciOiJIUzI1NiIsInR5cCI6IkpXVCJ9.eyJzdWIiOiIxMjM0NTY3ODkwIiwibmFtZSI6IkpvaG4gRG9lIn0.SflKxwRJSMeKKF2QT4fwpMeJf36POk6yJV_adQssw5c';\n18: "
    },
    {
      "type": "Hardcoded Password",
      "severity": "high",
      "file": "scanner/test/fixtures/fake_secrets.js",
      "line": 20,
      "value": "Sup3***********w0rd",
      "maskedValue": "Sup3***********w0rd",
      "category": "password",
      "ruleId": "hardcoded-password",
      "confidence": 0.7,
      "isTestFile": true,
      "hash": "e2a838dc8af249049b22be1eeeb798c58c2bbb5a087986fe67a2f54b764b482e",
      "snippet": "19: // Hardcoded password (fake) — actual JS assignment that regex can match\n20: const password = \"Sup3rS3cr3tPassw0rd\";\n21: "
    },
    {
      "type": "Slack Webhook URL",
      "severity": "high",
      "file": "scanner/test/fixtures/fake_secrets.js",
      "line": 29,
      "value": "http***************************************************************************xxxx",
      "maskedValue": "http***************************************************************************xxxx",
      "category": "api_key",
      "ruleId": "slack-webhook",
      "confidence": 0.99,
      "isTestFile": true,
      "hash": "c99ff66649400eb10adfefc048b4a074d3298fef5ba99c6aaa276999a2896cb7",
      "snippet": "28: // Slack webhook (fake)\n29: const slackWebhook = 'https://hooks.slack.com/services/TABCDEF123/BABCDEF456/xxxxxxxxxxxxxxxxxxxxxxxxxxxx';\n30: "
    },
    {
      "type": "SendGrid API Key",
      "severity": "high",
      "file": "scanner/test/fixtures/fake_secrets.js",
      "line": 38,
      "value": "SG.A**********************************************************6789",
      "maskedValue": "SG.A**********************************************************6789",
      "category": "api_key",
      "ruleId": "sendgrid-key",
      "confidence": 0.99,
      "isTestFile": true,
      "hash": "5f6f704cb6858e3d03f582dbaef3c339b05d9d4a73697fda26c1cd32765eaca3",
      "snippet": "37: // SendGrid key (fake)\n38: const sgKey = 'SG.ABCDEFGHIJKLMNOPQRSTUVWX.YZABCDEFGHIJKLMNOPQRSTUVWXYZ0123456789';\n39: "
    },
    {
      "type": "Generic API Key",
      "severity": "medium",
      "file": "backend/app/integrations/aws_integration.py",
      "line": 765,
      "value": "demo*******************************mnop",
      "maskedValue": "demo*******************************mnop",
      "category": "api_key",
      "ruleId": "generic-api-key",
      "confidence": 0.6,
      "isTestFile": false,
      "hash": "0715072b82e855f7eedc04d951b30f5bb24b5b89687a860b3184d8b7d3fa11e4",
      "snippet": "764:             \"config/settings.json\": '{\"database_url\": \"postgres://user:pass123@localhost/db\"}',\n765:             \"src/app.py\": 'API_KEY = \"demo_api_key_1234567890abcdefghijklmnop\"',\n766:             \".env.production\": 'AWS_ACCESS_KEY_ID=EXAMPLE_AWS_KEY_ID_12345\\nAWS_SECRET_ACCESS_KEY=example_aws_secret_key_placeholder'"
    },
    {
      "type": "Generic API Key",
      "severity": "medium",
      "file": "backend/app/scanner/s3_scanner.py",
      "line": 121,
      "value": "demo*******************************mnop",
      "maskedValue": "demo*******************************mnop",
      "category": "api_key",
      "ruleId": "generic-api-key",
      "confidence": 0.6,
      "isTestFile": false,
      "hash": "0715072b82e855f7eedc04d951b30f5bb24b5b89687a860b3184d8b7d3fa11e4",
      "snippet": "120:             (\"config/settings.json\", 2048, '{\"database_url\": \"postgres://user:pass123@localhost/db\"}'),\n121:             (\"src/api/auth.py\", 4096, 'API_KEY = \"demo_api_key_1234567890abcdefghijklmnop\"'),\n122:             (\".env.production\", 512, 'AWS_ACCESS_KEY_ID=EXAMPLE_AWS_KEY_ID_12345\\nAWS_SECRET_ACCESS_KEY=example_aws_secret_key_placeholder'),"
    },
    {
      "type": "Generic API Key",
      "severity": "medium",
      "file": "backend/app/scanner/s3_scanner.py",
      "line": 165,
      "value": "demo*****************************alue",
      "maskedValue": "demo*****************************alue",
      "category": "api_key",
      "ruleId": "generic-api-key",
      "confidence": 0.6,
      "isTestFile": false,
      "hash": "8e9eb5517506a280a1ef9d6ab78bfe3d1e63cdcecf34c82fc8036ed0e8630fd1",
      "snippet": "164: # WARNING: Hardcoded API key detected!\n165: STRIPE_API_KEY = \"demo_stripe_api_key_placeholder_value\"\n166: SENDGRID_KEY = \"SG.abcdefghijklmnop.qrstuvwxyz0123456789ABCDEFGH\""
    },
    {
      "type": "Generic API Key",
      "severity": "medium",
      "file": "backend/test_scanner.py",
      "line": 23,
      "value": "exam******************7890",
      "maskedValue": "exam******************7890",
      "category": "api_key",
      "ruleId": "generic-api-key",
      "confidence": 0.6,
      "isTestFile": true,
      "hash": "a83a47bf2585dcc979f228b0ed8b056fa00a44d12ebf6081b935a041938ee3a4",
      "snippet": "22: secret_key = \"example_secret_key_do_not_use_in_production\"\n23: api_key = \"example_api_key_1234567890\"\n24: password = \"super_secret_password123\""
    },
    {
      "type": "Generic API Key",
      "severity": "medium",
      "file": "scanner/test/fixtures/fake_secrets.js",
      "line": 23,
      "value": "AbCd********************1234",
      "maskedValue": "AbCd********************1234",
      "category": "api_key",
      "ruleId": "generic-api-key",
      "confidence": 0.6,
      "isTestFile": true,
      "hash": "e1709154178a5198f456bcc35d7fd36e4f7e8ce09aa9aa76fcdf92f8145656ed",
      "snippet": "22: // Generic API key (fake) — actual assignment\n23: const api_key = \"AbCdEfGhIjKlMnOpQrStUvWx1234\";\n24: "
    }
  ]
}